{"cameraMode":{"drawMode":0,"name":"Shaded","section":"Shading Mode"},"sceneLighting":true,"audioPlay":false,"sceneViewState":{"m_AlwaysRefresh":false,"showFog":true,"showSkybox":true,"showFlares":true,"showImageEffects":true,"showParticleSystems":true,"showVisualEffectGraphs":true,"m_FxEnabled":true},"in2DMode":false,"pivot":{"x":397.0968017578125,"y":357.619140625,"z":-30.3822021484375},"rotation":{"x":0.5457981824874878,"y":-0.07392767071723938,"z":0.0484425313770771,"w":0.8332526087760925},"size":332.29388427734377,"orthographic":true}